django_feature_flipper-0.1.3.dist-info/DESCRIPTION.rst
django_feature_flipper-0.1.3.dist-info/METADATA
django_feature_flipper-0.1.3.dist-info/RECORD
django_feature_flipper-0.1.3.dist-info/WHEEL
django_feature_flipper-0.1.3.dist-info/metadata.json
django_feature_flipper-0.1.3.dist-info/top_level.txt
feature_flipper/__init__.py
feature_flipper/admin.py
feature_flipper/apps.py
feature_flipper/flipper_settings.py
feature_flipper/models.py
feature_flipper/tests.py
feature_flipper/views.py
feature_flipper/migrations/0001_initial.py
feature_flipper/migrations/0002_auto_20160722_1028.py
feature_flipper/migrations/__init__.py
feature_flipper/templatetags/__init__.py
feature_flipper/templatetags/feature_flipper.py
