Metadata-Version: 2.0
Name: django-feature-flipper
Version: 0.1.3
Summary: A simple, customisable, feature flipper
Home-page: https://github.com/mypebble/django-feature-flipper.git
Author: Pebble
Author-email: scott.walton@mypebble.co.uk
License: MIT
Platform: UNKNOWN
Requires-Dist: django
